kiss/__init__.py
pyham_kiss-1.0.0.dist-info/LICENSE
pyham_kiss-1.0.0.dist-info/WHEEL
pyham_kiss-1.0.0.dist-info/METADATA
pyham_kiss-1.0.0.dist-info/RECORD
