Metadata-Version: 2.1
Name: pyham_kiss
Version: 1.0.0
Summary: KISS TNC Protocol Client for TCP/IP
Keywords: ham radio,amateur radio,packet radio,KISS,TNC,protocol
Author-email: Martin F N Cooper <mfncooper@gmail.com>
Requires-Python: >=3.7
Classifier: Development Status :: 5 - Production/Stable
Classifier: Intended Audience :: Developers
Classifier: License :: OSI Approved :: MIT License
Classifier: Programming Language :: Python :: 3 :: Only
Classifier: Topic :: Communications :: Ham Radio
Project-URL: Documentation, https://pyham_kiss.readthedocs.io
Project-URL: Source Code, https://github.com/mfncooper/pyham_kiss
